git_filter_repo.py
git_filter_repo-2.33.0.data/scripts/git-filter-repo
git_filter_repo-2.33.0.dist-info/METADATA
git_filter_repo-2.33.0.dist-info/WHEEL
git_filter_repo-2.33.0.dist-info/entry_points.txt
git_filter_repo-2.33.0.dist-info/top_level.txt
git_filter_repo-2.33.0.dist-info/RECORD
