Metadata-Version: 2.1
Name: git-filter-repo
Version: 2.33.0
Summary: Quickly rewrite git repository history
Home-page: https://github.com/newren/git-filter-repo
License: MIT
Project-URL: Source, https://github.com/newren/git-filter-repo
Project-URL: Issues, https://github.com/newren/git-filter-repo/issues/
Platform: any
Classifier: Development Status :: 4 - Beta
Classifier: Operating System :: OS Independent
Classifier: Programming Language :: Python
Classifier: License :: OSI Approved :: MIT License
Classifier: Programming Language :: Python :: 3.5
Classifier: Programming Language :: Python :: 3.6
Classifier: Programming Language :: Python :: 3.7
Classifier: Programming Language :: Python :: 3.8
Classifier: Programming Language :: Python :: 3
Classifier: Programming Language :: Python :: Implementation :: CPython
Classifier: Programming Language :: Python :: Implementation :: PyPy
Requires-Python: >=3.5
